potrace/__init__.py
potrace/potrace.py
potracer-0.0.4.dist-info/LICENSE
potracer-0.0.4.dist-info/METADATA
potracer-0.0.4.dist-info/WHEEL
potracer-0.0.4.dist-info/top_level.txt
potracer-0.0.4.dist-info/zip-safe
potracer-0.0.4.dist-info/RECORD
